pytest_github
